django_auth_app/__init__.py
django_auth_app/admin.py
django_auth_app/apps.py
django_auth_app/auth_views.py
django_auth_app/models.py
django_auth_app/tests.py
django_auth_app/urls.py
django_auth_app/views.py
django_auth_app/management/__init__.py
django_auth_app/management/__pycache__/__init__.cpython-310.pyc
django_auth_app/management/commands/__init__.py
django_auth_app/management/commands/copy_templates.py
django_auth_app/management/commands/__pycache__/__init__.cpython-310.pyc
django_auth_app/management/commands/__pycache__/copy_templates.cpython-310.pyc
django_auth_app/migrations/__init__.py
django_auth_app/templates/django_auth_app/dashboard.html
django_auth_app/templates/django_auth_app/home_page.html
django_auth_app/templates/django_auth_app/login.html
django_auth_app/templates/django_auth_app/register.html
django_auth_package/__init__.py
django_auth_package/asgi.py
django_auth_package/settings.py
django_auth_package/urls.py
django_auth_package/wsgi.py
django_auto_authentication-0.1.0.dist-info/METADATA
django_auto_authentication-0.1.0.dist-info/WHEEL
django_auto_authentication-0.1.0.dist-info/top_level.txt
django_auto_authentication-0.1.0.dist-info/RECORD
