Metadata-Version: 2.4
Name: django_auto_authentication
Version: 0.1.0
Summary: Reusable Django authentication package: login, register, dashboard ready out-of-the-box!
Home-page: https://github.com/jagritiS/django_auto_authentication
Author: Jagriti Srivastava
Author-email: Jagriti Srivastava <jagritisrvstv@gmail.com>
License-Expression: MIT
Project-URL: Homepage, https://github.com/jagritiS/django_auth_package
Project-URL: Issues, https://github.com/jagritiS/django_auth_package/issues
Classifier: Programming Language :: Python :: 3
Classifier: Framework :: Django
Classifier: Operating System :: OS Independent
Classifier: Development Status :: 5 - Production/Stable
Classifier: Intended Audience :: Developers
Classifier: Topic :: Software Development :: Libraries :: Python Modules
Requires-Python: >=3.10
Requires-Dist: Django>=4.0
Dynamic: author
Dynamic: home-page
Dynamic: requires-python
